sigmf/__init__.py
sigmf/archive.py
sigmf/archivereader.py
sigmf/error.py
sigmf/hashing.py
sigmf/schema-collection.json
sigmf/schema-meta.json
sigmf/schema.py
sigmf/sigmffile.py
sigmf/utils.py
sigmf/validate.py
sigmf/convert/__init__.py
sigmf/convert/__main__.py
sigmf/convert/blue.py
sigmf/convert/wav.py
sigmf-1.7.0.dist-info/METADATA
sigmf-1.7.0.dist-info/WHEEL
sigmf-1.7.0.dist-info/entry_points.txt
sigmf-1.7.0.dist-info/top_level.txt
sigmf-1.7.0.dist-info/RECORD
