Metadata-Version: 2.4
Name: SigMF
Version: 1.7.0
Summary: Easily interact with Signal Metadata Format (SigMF) recordings.
License:                    GNU LESSER GENERAL PUBLIC LICENSE
Project-URL: repository, https://github.com/sigmf/sigmf-python
Project-URL: documentation, https://sigmf.readthedocs.io/en/latest/
Project-URL: issues, https://github.com/sigmf/sigmf-python/issues
Project-URL: Specification (HTML), https://sigmf.org/
Project-URL: Specification (PDF), https://sigmf.github.io/SigMF/sigmf-spec.pdf
Project-URL: Specification (Repo), https://github.com/sigmf/SigMF
Keywords: gnuradio,radio
Classifier: Development Status :: 5 - Production/Stable
Classifier: License :: OSI Approved :: GNU Lesser General Public License v3 or later (LGPLv3+)
Classifier: Operating System :: OS Independent
Classifier: Programming Language :: Python :: 3
Classifier: Programming Language :: Python :: 3.7
Classifier: Programming Language :: Python :: 3.8
Classifier: Programming Language :: Python :: 3.9
Classifier: Programming Language :: Python :: 3.10
Classifier: Programming Language :: Python :: 3.11
Classifier: Programming Language :: Python :: 3.12
Classifier: Programming Language :: Python :: 3.13
Classifier: Programming Language :: Python :: 3.14
Classifier: Topic :: Scientific/Engineering
Classifier: Topic :: Communications :: Ham Radio
Requires-Python: >=3.7
Requires-Dist: numpy
Requires-Dist: jsonschema
Provides-Extra: test
Requires-Dist: pylint; extra == "test"
Requires-Dist: pytest; extra == "test"
Requires-Dist: pytest-cov; extra == "test"
Requires-Dist: hypothesis; extra == "test"
